Metadata-Version: 2.1
Name: pyb3
Version: 0.0.1
Summary: B3 (b3.com.br) API wrapper.
Home-page: https://github.com/victormpa/pyb3
Author: Victor Martins
Author-email: victor.martins.dpaula@gmail.com
License: UNKNOWN
Project-URL: Bug Tracker, https://github.com/victormpa/pyb3/issues
Platform: UNKNOWN
Classifier: Development Status :: 1 - Planning
Classifier: Programming Language :: Python :: 3
Classifier: Programming Language :: Python :: 3.9
Classifier: License :: OSI Approved :: Apache Software License
Requires-Python: >=3.9
License-File: LICENSE
